lutstrings/__init__.py
lutstrings/lut.py
lutstrings/test_init_string.py
lutstrings-0.1.4.dist-info/LICENSE
lutstrings-0.1.4.dist-info/METADATA
lutstrings-0.1.4.dist-info/WHEEL
lutstrings-0.1.4.dist-info/top_level.txt
lutstrings-0.1.4.dist-info/RECORD
