Metadata-Version: 2.1
Name: lutstrings
Version: 0.1.4
Summary: Python package to reorder init strings
Home-page: https://github.com/byuccl/encrypted_ip/tree/main/lutstrings
Author: Daniel Hutchings
Author-email: dhutch@dazoo.org
License: MIT
Platform: UNKNOWN
Classifier: Development Status :: 1 - Planning
License-File: LICENSE
